deepsel/__init__.py
deepsel/py.typed
deepsel/sqlalchemy/__init__.py
deepsel/sqlalchemy/db_manager.py
deepsel-0.3.0.dist-info/licenses/LICENSE
deepsel-0.3.0.dist-info/METADATA
deepsel-0.3.0.dist-info/WHEEL
deepsel-0.3.0.dist-info/top_level.txt
deepsel-0.3.0.dist-info/RECORD
