Metadata-Version: 2.4
Name: deepsel
Version: 0.3.0
Summary: Database utilities and authentication framework for SQLAlchemy, FastAPI Python applications
Author-email: "Deepsel Inc." <info@deepsel.com>
License: MIT
Project-URL: Homepage, https://github.com/DeepselSystems/deepsel
Project-URL: Repository, https://github.com/DeepselSystems/deepsel
Project-URL: Issues, https://github.com/DeepselSystems/deepsel/issues
Keywords: sqlalchemy,database,migration,schema,postgres,deepsel
Classifier: Development Status :: 4 - Beta
Classifier: Intended Audience :: Developers
Classifier: License :: OSI Approved :: MIT License
Classifier: Programming Language :: Python :: 3
Classifier: Programming Language :: Python :: 3.12
Classifier: Topic :: Database
Classifier: Framework :: FastAPI
Classifier: Framework :: Pydantic
Classifier: Topic :: Software Development :: Libraries :: Python Modules
Requires-Python: >=3.12
License-File: LICENSE
Requires-Dist: sqlalchemy>=2.0.30
Provides-Extra: dev
Requires-Dist: pytest>=8.3.5; extra == "dev"
Requires-Dist: pytest-cov>=7.0.0; extra == "dev"
Requires-Dist: black>=25.0.0; extra == "dev"
Requires-Dist: flake8>=7.2.0; extra == "dev"
Requires-Dist: bandit>=1.8.0; extra == "dev"
Requires-Dist: build>=0.10.0; extra == "dev"
Requires-Dist: twine>=6.2.0; extra == "dev"
Requires-Dist: testcontainers[postgres]>=4.0.0; extra == "dev"
Requires-Dist: psycopg[binary]>=3.1.0; extra == "dev"
Dynamic: license-file
